README.md
allocGPU.py
setup.py
allocGPU.egg-info/PKG-INFO
allocGPU.egg-info/SOURCES.txt
allocGPU.egg-info/dependency_links.txt
allocGPU.egg-info/requires.txt
allocGPU.egg-info/top_level.txt